tql/__init__.py
tql/analyzer.py
tql/cache/__init__.py
tql/cache/base.py
tql/cache/memory.py
tql/cache/redis.py
tql/cli.py
tql/core.py
tql/core_components/README.md
tql/core_components/__init__.py
tql/core_components/file_operations.py
tql/core_components/opensearch_operations.py
tql/core_components/stats_operations.py
tql/core_components/validation_operations.py
tql/evaluator.py
tql/evaluator_components/README.md
tql/evaluator_components/__init__.py
tql/evaluator_components/field_access.py
tql/evaluator_components/special_expressions.py
tql/evaluator_components/value_comparison.py
tql/exceptions.py
tql/field_type_inference.py
tql/geoip_normalizer.py
tql/mutator_analyzer.py
tql/mutators/__init__.py
tql/mutators/base.py
tql/mutators/dns.py
tql/mutators/encoding.py
tql/mutators/geo.py
tql/mutators/list.py
tql/mutators/network.py
tql/mutators/security.py
tql/mutators/string.py
tql/opensearch.py
tql/opensearch_components/README.md
tql/opensearch_components/__init__.py
tql/opensearch_components/field_mapping.py
tql/opensearch_components/lucene_converter.py
tql/opensearch_components/query_converter.py
tql/opensearch_mappings.py
tql/opensearch_stats.py
tql/parser.py
tql/parser_components/README.md
tql/parser_components/__init__.py
tql/parser_components/ast_builder.py
tql/parser_components/error_analyzer.py
tql/parser_components/field_extractor.py
tql/parser_components/grammar.py
tql/post_processor.py
tql/scripts.py
tql/stats_evaluator.py
tql/stats_transformer.py
tql/streaming_file_processor.py
tql/validators.py
tellaro_query_language-0.2.17.dist-info/METADATA
tellaro_query_language-0.2.17.dist-info/WHEEL
tellaro_query_language-0.2.17.dist-info/entry_points.txt
tellaro_query_language-0.2.17.dist-info/licenses/LICENSE
tellaro_query_language-0.2.17.dist-info/RECORD
