Metadata-Version: 2.4
Name: tellaro-query-language
Version: 0.2.17
Summary: A flexible, human-friendly query language for searching and filtering structured data
License: Proprietary
License-File: LICENSE
Keywords: query,language,opensearch,elasticsearch,search,filter,tql
Author: Justin Henderson
Author-email: justin@tellaro.io
Requires-Python: >=3.11,<3.14
Classifier: Development Status :: 4 - Beta
Classifier: Intended Audience :: Developers
Classifier: License :: Other/Proprietary License
Classifier: Programming Language :: Python :: 3
Classifier: Programming Language :: Python :: 3.11
Classifier: Programming Language :: Python :: 3.12
Classifier: Programming Language :: Python :: 3.13
Classifier: Topic :: Software Development :: Libraries :: Python Modules
Classifier: Topic :: Text Processing :: Linguistic
Provides-Extra: opensearch
Requires-Dist: dnspython (>=2.8.0,<3.0.0)
Requires-Dist: maxminddb (>=3.0.0,<4.0.0)
Requires-Dist: opensearch-dsl (>=2.1.0,<3.0.0) ; extra == "opensearch"
Requires-Dist: opensearch-py (>=2.8.0,<3.0.0) ; extra == "opensearch"
Requires-Dist: pyparsing (>=3.3.0,<4.0.0)
Requires-Dist: setuptools (>=80.9.0,<81.0.0)
Requires-Dist: urllib3 (>=2.6.0,<3.0.0)
Project-URL: Documentation, https://github.com/tellaro/tellaro-query-language/tree/main/docs
Project-URL: Homepage, https://github.com/tellaro/tellaro-query-language
Project-URL: Repository, https://github.com/tellaro/tellaro-query-language
